baselog/__init__.py
baselog/decorators.py
baselog/errors.py
baselog/event.py
baselog/helpers.py
baselog/logger.py
baselog/logger_manager.py
baselog/sync_client.py
baselog/api/__init__.py
baselog/api/auth.py
baselog/api/client.py
baselog/api/config.py
baselog/api/exceptions.py
baselog/api/models.py
baselog/api/responses.py
baselog_py-1.0.0.dist-info/METADATA
baselog_py-1.0.0.dist-info/WHEEL
baselog_py-1.0.0.dist-info/top_level.txt
baselog_py-1.0.0.dist-info/RECORD
