Metadata-Version: 2.4
Name: baselog-py
Version: 1.0.0
Summary: Add your description here
Requires-Python: >=3.12
Requires-Dist: httpx>=0.28.1
Requires-Dist: pytest>=8.4.2
Requires-Dist: pytest-asyncio>=1.2.0
Requires-Dist: pytest-cov>=7.0.0
Requires-Dist: tenacity>=9.1.2
Requires-Dist: typing-extensions>=4.15.0
